isfhyfp/__init__.py
isfhyfp/custom_log.py
isfhyfp/pushMsg.py
isfhyfp/tools.py
isfhyfp-1.1.0.dist-info/METADATA
isfhyfp-1.1.0.dist-info/WHEEL
isfhyfp-1.1.0.dist-info/top_level.txt
isfhyfp-1.1.0.dist-info/RECORD
